LICENSE
MANIFEST.in
README.rst
autolink.py
setup.py
autolink.egg-info/PKG-INFO
autolink.egg-info/SOURCES.txt
autolink.egg-info/dependency_links.txt
autolink.egg-info/requires.txt
autolink.egg-info/top_level.txt